{"results": [{"hits": [], "page": 24, "nbHits": 0, "nbPages": 0, "hitsPerPage": 42, "exhaustiveNbHits": true, "processingTimeMS": 1, "message": "you can only fetch the 1000 hits for this query. You can extend the number of hits returned via the paginationLimitedTo index parameter or use the browse method. You can read our FAQ for more details about browsing: https://www.algolia.com/doc/faq/index-configuration/how-can-i-retrieve-all-the-records-in-my-index", "query": "*", "params": "query=*&hitsPerPage=42&page=24&facets=*&facetFilters=%5B%22inStock%3A1%22%2C%22approvalStatus%3A1%22%2C%22allCategories%3Acpwomen-clothing-tops-tshirtsandvests%22%2C%22badge.title.en%3A-LASTCHANCE%22%5D&getRankingInfo=1&clickAnalytics=true&attributesToHighlight=null&analyticsTags=%5B%22cpwomen-clothing-tops-tshirtsandvests%22%2C%22en%22%5D&attributesToRetrieve=concept%2CmanufacturerName%2Curl%2C333WX493H%2C345WX345H%2C505WX316H%2C550WX550H%2C499WX739H%2Cbadge%2Cname%2Csummary%2CwasPrice%2Cprice%2CemployeePrice%2CshowMoreColor%2CproductType%2CchildDetail%2Csibiling%2CthumbnailImg%2CgallaryImages%2CisConceptDelivery&numericFilters=price%20%3E%201.9&query=*&maxValuesPerFacet=500&tagFilters=%5B%5B%22babyshop%22%2C%22splash%22%2C%22lifestyle%22%2C%22shoemart%22%2C%22centrepoint%22%2C%22shoexpress%22%2C%22lipsy%22%2C%22sportsone%22%2C%22sminternational%22%5D%5D&filters=price+%3E0", "index": "prod_sa_centrepoint_Product", "queryID": "2b86243c8946597855155e3043c5e717"}]}